htms_obj/__init__.py
htms_obj/htms_par_obj.py
htms_obj/htorm.py
htms_obj-2.3.1.dist-info/LICENSE
htms_obj-2.3.1.dist-info/METADATA
htms_obj-2.3.1.dist-info/WHEEL
htms_obj-2.3.1.dist-info/top_level.txt
htms_obj-2.3.1.dist-info/RECORD
