Metadata-Version: 2.1
Name: htms-obj
Version: 2.3.1
Summary: Hyper Table Management System (HTMS) - high level API
Home-page: https://github.com/Arselon/HTMS
Author: Arslan Aliev
Author-email: arslanaliev@yahoo.com
Maintainer: Arslan Aliev
Maintainer-email: arslanaliev@yahoo.com
License: Apache
Keywords: HTMS,dbms,API,high level,object-htdb mapping,OOP
Platform: UNKNOWN
Classifier: Programming Language :: Python :: 3.7
Classifier: Intended Audience :: Developers
Requires-Python: >=3.7
Requires-Dist: cage-api (>=2.10.0)
Requires-Dist: htms-low-api (>=2.3.1)
Requires-Dist: htms-mid-api (>=2.3.1)
